resifdatareporter/__init__.py
resifdatareporter/resifdatareporter.py
resifdatareporter-0.7.9.dist-info/LICENSE
resifdatareporter-0.7.9.dist-info/METADATA
resifdatareporter-0.7.9.dist-info/WHEEL
resifdatareporter-0.7.9.dist-info/entry_points.txt
resifdatareporter-0.7.9.dist-info/top_level.txt
resifdatareporter-0.7.9.dist-info/RECORD
