Metadata-Version: 2.1
Name: resifdatareporter
Version: 0.7.9
Summary: Scans the resif data repository and compute metrics. Sends the result in influxdb or postgres
Home-page: https://gricad-gitlab.univ-grenoble-alpes.fr/OSUG/RESIF/resif_data_reporter
Author: Jonathan Schaeffer
Author-email: jonathan.schaeffer@univ-grenoble-alpes.fr
Maintainer: Jonathan Schaeffer
Maintainer-email: jonathan.schaeffer@univ-grenoble-alpes.fr
License: GPL-3.0
Platform: UNKNOWN
Classifier: Development Status :: 4 - Beta
Classifier: Intended Audience :: Developers
Classifier: License :: OSI Approved :: GNU General Public License v3 or later (GPLv3+)
Classifier: Natural Language :: English
Classifier: Operating System :: OS Independent
Classifier: Programming Language :: Python :: 3.6
Classifier: Programming Language :: Python :: 3.7
Requires-Dist: fdsnextender (>=0.3.2)
Requires-Dist: Click (==7.0)
Requires-Dist: python-dateutil (==2.7.5)
Requires-Dist: PyYAML (==5.1)
Requires-Dist: psycopg2-binary (==2.7.6.1)
Requires-Dist: influxdb (==5.2.1)
